{
  "indexes": [
    {
      "collectionGroup": "bankAccounts",
      "queryScope": "COLLECTION",
      "fields": [
        {
          "fieldPath": "eventMakerId",
          "order": "ASCENDING"
        },
        {
          "fieldPath": "createdAt",
          "order": "DESCENDING"
        }
      ]
    },
    {
      "collectionGroup": "events",
      "queryScope": "COLLECTION",
      "fields": [
        {
          "fieldPath": "state",
          "order": "ASCENDING"
        },
        {
          "fieldPath": "releaseDate",
          "order": "ASCENDING"
        }
      ]
    },
    {
      "collectionGroup": "events",
      "queryScope": "COLLECTION",
      "fields": [
        {
          "fieldPath": "state",
          "order": "ASCENDING"
        },
        {
          "fieldPath": "releaseDate",
          "order": "ASCENDING"
        },
        {
          "fieldPath": "highlighted",
          "order": "ASCENDING"
        }
      ]
    },
    {
      "collectionGroup": "mobilePayments",
      "queryScope": "COLLECTION",
      "fields": [
        {
          "fieldPath": "eventMakerId",
          "order": "ASCENDING"
        },
        {
          "fieldPath": "createdAt",
          "order": "DESCENDING"
        }
      ]
    },
    {
      "collectionGroup": "purchasedTickets",
      "queryScope": "COLLECTION",
      "fields": [
        {
          "fieldPath": "eventMakerId",
          "order": "ASCENDING"
        },
        {
          "fieldPath": "purchaseDate",
          "order": "DESCENDING"
        }
      ]
    },
    {
      "collectionGroup": "ticketPurchases",
      "queryScope": "COLLECTION",
      "fields": [
        {
          "fieldPath": "eventId",
          "order": "ASCENDING"
        },
        {
          "fieldPath": "purchaseDate",
          "order": "ASCENDING"
        }
      ]
    },
    {
      "collectionGroup": "transactions",
      "queryScope": "COLLECTION",
      "fields": [
        {
          "fieldPath": "eventMakerId",
          "order": "ASCENDING"
        },
        {
          "fieldPath": "createdAt",
          "order": "DESCENDING"
        }
      ]
    },
    {
      "collectionGroup": "withdrawalRequests",
      "queryScope": "COLLECTION",
      "fields": [
        {
          "fieldPath": "eventMakerId",
          "order": "ASCENDING"
        },
        {
          "fieldPath": "requestedAt",
          "order": "DESCENDING"
        }
      ]
    },
    {
      "collectionGroup": "users",
      "queryScope": "COLLECTION",
      "fields": [
        {
          "fieldPath": "email",
          "order": "ASCENDING"
        },
        {
          "fieldPath": "isActive",
          "order": "ASCENDING"
        }
      ]
    },
    {
      "collectionGroup": "users",
      "queryScope": "COLLECTION",
      "fields": [
        {
          "fieldPath": "nif",
          "order": "ASCENDING"
        },
        {
          "fieldPath": "isActive",
          "order": "ASCENDING"
        }
      ]
    },
    {
      "collectionGroup": "services",
      "queryScope": "COLLECTION",
      "fields": [
        {
          "fieldPath": "providerId",
          "order": "ASCENDING"
        },
        {
          "fieldPath": "isActive",
          "order": "ASCENDING"
        }
      ]
    },
    {
      "collectionGroup": "services",
      "queryScope": "COLLECTION",
      "fields": [
        {
          "fieldPath": "isActive",
          "order": "ASCENDING"
        },
        {
          "fieldPath": "createdAt",
          "order": "DESCENDING"
        }
      ]
    },
    {
      "collectionGroup": "bookings",
      "queryScope": "COLLECTION",
      "fields": [
        {
          "fieldPath": "clientId",
          "order": "ASCENDING"
        },
        {
          "fieldPath": "createdAt",
          "order": "DESCENDING"
        }
      ]
    },
    {
      "collectionGroup": "bookings",
      "queryScope": "COLLECTION",
      "fields": [
        {
          "fieldPath": "providerId",
          "order": "ASCENDING"
        },
        {
          "fieldPath": "createdAt",
          "order": "DESCENDING"
        }
      ]
    },
    {
      "collectionGroup": "bookings",
      "queryScope": "COLLECTION",
      "fields": [
        {
          "fieldPath": "status",
          "order": "ASCENDING"
        },
        {
          "fieldPath": "createdAt",
          "order": "DESCENDING"
        }
      ]
    },
    {
      "collectionGroup": "bookings",
      "queryScope": "COLLECTION",
      "fields": [
        {
          "fieldPath": "clientId",
          "order": "ASCENDING"
        },
        {
          "fieldPath": "status",
          "order": "ASCENDING"
        },
        {
          "fieldPath": "createdAt",
          "order": "DESCENDING"
        }
      ]
    },
    {
      "collectionGroup": "bookings",
      "queryScope": "COLLECTION",
      "fields": [
        {
          "fieldPath": "providerId",
          "order": "ASCENDING"
        },
        {
          "fieldPath": "status",
          "order": "ASCENDING"
        },
        {
          "fieldPath": "createdAt",
          "order": "DESCENDING"
        }
      ]
    }
  ],
  "fieldOverrides": []
}